mesh/__init__.py
mesh/connectors/__init__.py
mesh/connectors/base.py
mesh/connectors/postgres.py
mesh/dataframes/__init__.py
mesh/dataframes/drift_detector.py
mesh/dataframes/frame_operators.py
mesh/dataframes/row_operations.py
mesh/dataframes/validators.py
mesh/dates/__init__.py
mesh/dates/wrangler.py
mesh/forecasters/__init__.py
mesh/forecasters/confidence_interval.py
mesh/google/__init__.py
mesh/google/connectors/__init__.py
mesh/google/connectors/bigquery.py
mesh/google/connectors/gcs.py
mesh/google/deploy_k8s.sh
mesh/google/secrets.py
mesh/logger.py
mesh/metrics/__init__.py
mesh/metrics/mase.py
mesh/notifiers/__init__.py
mesh/notifiers/gchatter.py
mesh/notifiers/slackrapper.py
mesh/pipeline.py
mesh/projects/__init__.py
mesh/projects/context.py
mesh/projects/conventions.py
mesh/stores.py
analytics_mesh-1.0.0.dist-info/LICENSE
analytics_mesh-1.0.0.dist-info/METADATA
analytics_mesh-1.0.0.dist-info/WHEEL
analytics_mesh-1.0.0.dist-info/RECORD
