Metadata-Version: 2.1
Name: analytics-mesh
Version: 1.0.0
Summary: Facades and common functions necessary for data science and data engineering workflows
Home-page: https://gitlab.com/spatialedge/ml-engineering/analytics
License: Spatialedge Community License
Keywords: analytics,utilities
Author: Jacques du Toit, Carl du Plessis, Jean Naudé, Lydia de Lange, Bernie Lindner
Requires-Python: >=3.9,<3.11
Classifier: Environment :: Console
Classifier: Intended Audience :: Developers
Classifier: License :: Other/Proprietary License
Classifier: Programming Language :: Python :: 3
Classifier: Programming Language :: Python :: 3.9
Classifier: Programming Language :: Python :: 3.10
Classifier: Topic :: Scientific/Engineering :: Information Analysis
Classifier: Topic :: Utilities
Requires-Dist: PyYAML (>=5.1.2)
Requires-Dist: anybadge (>=1.7.0)
Requires-Dist: coverage (>=4.5.4)
Requires-Dist: deprecation (>=2.1.0)
Requires-Dist: fsspec (>=2021.6.1)
Requires-Dist: gcsfs (>=2021.6.1)
Requires-Dist: google-cloud-bigquery (>=2.2.0)
Requires-Dist: google-cloud-bigquery-storage (==2.13.2)
Requires-Dist: google-cloud-secret-manager (>=2.0.0)
Requires-Dist: google-cloud-storage (>=1.24.1)
Requires-Dist: httplib2 (>=0.20.4)
Requires-Dist: joblib (>=1.0.1)
Requires-Dist: numpy (>=1.19.5,<2.0.0)
Requires-Dist: pandas (>=2.2.0)
Requires-Dist: poetry-dynamic-versioning (>=1.4.0,<2.0.0)
Requires-Dist: pre-commit (>=2.13.0)
Requires-Dist: psycopg2-binary (==2.8.5)
Requires-Dist: pylint (>=2.6.0)
Requires-Dist: pylint-exit (>=1.2.0)
Requires-Dist: python-box (>=5.1.1)
Requires-Dist: python-dateutil (>=2.8.0)
Requires-Dist: pytz (>=2019.2)
Requires-Dist: scikit-learn (>=0.24.2)
Requires-Dist: scipy (>=1.10.1)
Requires-Dist: slack-alerts (>=1.0.0)
Requires-Dist: twine (>=5.1.1,<6.0.0)
Project-URL: Repository, https://gitlab.com/spatialedge/ml-engineering/analytics
